onlinesimru/__init__.py
onlinesimru/api.py
onlinesimru/driver.py
onlinesimru/exceptions.py
onlinesimru/services/__init__.py
onlinesimru/services/free_numbers_service.py
onlinesimru/services/proxy_service.py
onlinesimru/services/rent_numbers_service.py
onlinesimru/services/temp_numbers_service.py
onlinesimru/services/user_service.py
onlinesimru/types/__init__.py
onlinesimru/types/rent_numbers_types.py
onlinesimru-2.1.3.dist-info/licenses/LICENSE
onlinesimru-2.1.3.dist-info/METADATA
onlinesimru-2.1.3.dist-info/WHEEL
onlinesimru-2.1.3.dist-info/top_level.txt
onlinesimru-2.1.3.dist-info/RECORD
