Metadata-Version: 2.4
Name: onlinesimru
Version: 2.1.3
Summary: Wrapper for automatic reception of SMS-messages by onlinesim.ru
Author-email: s00d <suppport@onlinesim.ru>
Maintainer-email: s00d <suppport@onlinesim.ru>
License-Expression: Apache-2.0
Project-URL: Homepage, https://github.com/s00d/onlinesim-python-api
Project-URL: Documentation, https://github.com/s00d/onlinesim-python-api/wiki
Project-URL: Repository, https://github.com/s00d/onlinesim-python-api
Project-URL: Bug Tracker, https://github.com/s00d/onlinesim-python-api/issues
Project-URL: Download, https://github.com/s00d/onlinesim-python-api/archive/master.zip
Keywords: sms,receive,onlinesim-ru,autoreg
Classifier: Operating System :: OS Independent
Classifier: Environment :: Console
Classifier: Development Status :: 4 - Beta
Classifier: Programming Language :: Python
Classifier: Programming Language :: Python :: 3
Classifier: Programming Language :: Python :: 3.7
Classifier: Programming Language :: Python :: 3.8
Classifier: Programming Language :: Python :: 3.9
Classifier: Programming Language :: Python :: 3.10
Classifier: Programming Language :: Python :: 3.11
Classifier: Programming Language :: Python :: 3.12
Classifier: Programming Language :: Python :: 3 :: Only
Classifier: Programming Language :: Python :: Implementation :: CPython
Classifier: Topic :: Communications
Classifier: Topic :: Internet
Classifier: Topic :: Software Development :: Libraries :: Python Modules
Requires-Python: >=3.7
License-File: LICENSE
Requires-Dist: httpx
Requires-Dist: dacite
Requires-Dist: pydantic<3.0.0,>=1.10.0
Dynamic: license-file
